setup.py
SeleniumRunner.egg-info/PKG-INFO
SeleniumRunner.egg-info/SOURCES.txt
SeleniumRunner.egg-info/dependency_links.txt
SeleniumRunner.egg-info/entry_points.txt
SeleniumRunner.egg-info/requires.txt
SeleniumRunner.egg-info/top_level.txt
sr/__about__.py
sr/__init__.py
sr/cli.py
sr/common.py
sr/config.py
sr/conftest.py
sr/location.py
sr/logger.py
sr/wdriver.py