Metadata-Version: 1.0
Name: SeleniumRunner
Version: 1.0.3
Summary: write a yaml to test selenium
Home-page: https://github.com/xinxi1990/SeleniumRunner
Author: xinxi
Author-email: xinxi1990@163.com
License: MIT Licence
Keywords: pip,SeleniumRunner,Selenium
Platform: any
